django_chelseru-2.0.4.dist-info/licenses/LICENSE
drfchelseru/__init__.py
drfchelseru/admin.py
drfchelseru/apps.py
drfchelseru/consumers.py
drfchelseru/middlewares.py
drfchelseru/models.py
drfchelseru/routing.py
drfchelseru/serializers.py
drfchelseru/services.py
drfchelseru/settings.py
drfchelseru/signals.py
drfchelseru/tests.py
drfchelseru/urls.py
drfchelseru/validators.py
drfchelseru/views.py
drfchelseru/migrations/0001_initial.py
drfchelseru/migrations/0002_otpcode_session_user.py
drfchelseru/migrations/0003_rename_mobile_otpcode_mobile_number.py
drfchelseru/migrations/0004_rename_message_message_sms.py
drfchelseru/migrations/0005_rename_message_sms_messagesms_chatroom_messagechat.py
drfchelseru/migrations/0006_alter_chatroom_user_1_alter_chatroom_user_2_and_more.py
drfchelseru/migrations/0007_chatroom_pinned_for_chatroom_status_chatroom_users_and_more.py
drfchelseru/migrations/0008_alter_chatroompermissions_user.py
drfchelseru/migrations/0009_alter_chatroom_status.py
drfchelseru/migrations/0010_chatroom_banneds_chatroom_descriptions_chatroom_name_and_more.py
drfchelseru/migrations/0011_alter_chatroom_user_1_alter_chatroom_user_2.py
drfchelseru/migrations/0012_payment.py
drfchelseru/migrations/0013_payment_authority_payment_data_payment_status_code.py
drfchelseru/migrations/0014_payment_gateway_title_payment_gateway_url.py
drfchelseru/migrations/0015_payment_message.py
drfchelseru/migrations/0016_payment_card_hash_payment_card_pan_and_more.py
drfchelseru/migrations/0017_alter_payment_callback_url_alter_payment_gateway_url.py
drfchelseru/migrations/0018_alter_payment_ref_id.py
drfchelseru/migrations/0019_payment_created_at_payment_status_payment_updated_at.py
drfchelseru/migrations/0020_payment_paid_at.py
drfchelseru/migrations/0021_alter_payment_message.py
drfchelseru/migrations/0022_payment_pay_mode_wallet.py
drfchelseru/migrations/__init__.py
django_chelseru-2.0.4.dist-info/METADATA
django_chelseru-2.0.4.dist-info/WHEEL
django_chelseru-2.0.4.dist-info/top_level.txt
django_chelseru-2.0.4.dist-info/RECORD
