Metadata-Version: 2.4
Name: django-chelseru
Version: 2.0.4
Summary: Authentication system, online and real-time chat, SMS & BANK system for Iranian SMS services.
Home-page: https://pipdjango.chelseru.com
Author: Sobhan Bahman Rashnu
Author-email: bahmanrashnu@gmail.com
Project-URL: Documentation, https://github.com/Chelseru/django-chelseru-lour/
Project-URL: Telegram Group, https://t.me/bahmanpy
Project-URL: Telegram Channel, https://t.me/ChelseruCom
Keywords: djangochelseruchat djangochat drfchat online-chat online real-time chat iran chelseru lor lur bahman rashnu rashno lak lour sms djangoauth auth ywt otpauth otp authentication djangootp djangoiransms iransms djangosms djangokavenegar djangomelipayamak sobhan چت  سبحان بهمن رشنو چلسرو جنگو پایتون لر لور آنلاین ریل تایم
Classifier: Programming Language :: Python :: 3
Classifier: Framework :: Django
Classifier: License :: OSI Approved :: MIT License
Classifier: Operating System :: OS Independent
Requires-Python: >=3.11
License-File: LICENSE
Requires-Dist: Django>=5.1.6
Requires-Dist: djangorestframework==3.15.2
Requires-Dist: djangorestframework_simplejwt==5.5.0
Requires-Dist: channels==4.2.2
Requires-Dist: channels_redis==4.2.1
Requires-Dist: daphne==4.1.2
Requires-Dist: zeep==4.3.1
Requires-Dist: user-agents==2.2.0
Dynamic: author
Dynamic: author-email
Dynamic: classifier
Dynamic: description
Dynamic: description-content-type
Dynamic: home-page
Dynamic: keywords
Dynamic: license-file
Dynamic: project-url
Dynamic: requires-dist
Dynamic: requires-python
Dynamic: summary
